[
  {
    "name": "Sunset Bistro",
    "stars": 4.5,
    "description": "Fine dining with a sunset view.",
    "price": 60,
    "website": "https://reservation.com/sunset",
    "image": "/assets/sunset.jpg"
  },
  {
    "name": "Green Garden Cafe",
    "stars": 4.0,
    "description": "Organic meals in a garden setting.",
    "price": 45,
    "website": "https://reservation.com/greengarden",
    "image": "/assets/garden.jpg"
  },
  {
    "name": "City Noodle House",
    "stars": 4.2,
    "description": "Authentic Asian noodles in the city center.",
    "price": 35,
    "website": "https://reservation.com/noodlehouse",
    "image": "/assets/noodle.jpg"
  }
]